{
  "services": [
    {
      "name": "Basic",
      "cpu": "Intel® Xeon® E5 2697v3",
      "ram": "3GB",
      "storage": "SSD NVMe",
      "port": "10Gbps",
      "firewall": "AntiDDoS Pro",
      "price": "25,000 VND"
    },
    {
      "name": "Balanced",
      "cpu": "Intel® Xeon® Gold 6150",
      "ram": "2GB",
      "storage": "SSD NVMe",
      "port": "10Gbps",
      "firewall": "AntiDDoS Pro",
      "price": "60,000 VND"
    },
    {
      "name": "High Performance",
      "cpu": "AMD® Ryzen™ 9 9900X/9950X",
      "ram": "8GB",
      "storage": "SSD NVMe",
      "port": "10Gbps",
      "firewall": "AntiDDoS Pro",
      "price": "400,000 VND"
    }
  ],
  "feedbacks": [
    {
      "user": "PHAM THANH CONG",
      "avatar": "Admin.jpg",
      "comment": "DEVELOPER / TESTER"
    }
  ]
}
